{
  "qid": "ramdocs_000108",
  "question": "100 Squadron was formed in which country?",
  "cards": [
    {
      "doc_id": "D1",
      "relevance": "high",
      "answer_candidate": "Australia",
      "normalized_answer": "australia",
      "claim": "No. 100 Squadron was formed in Australia.",
      "temporal_status": "current",
      "time_cue": "15 February 1942",
      "confidence": 1.0,
      "raw_quote": "No. 100 Squadron was formed at RAAF Station Richmond, New South Wales, on 15 February 1942",
      "rationale": "The document specifies the formation location as RAAF Station Richmond, New South Wales, which is in Australia.",
      "entity_explicitness": "unknown",
      "answer_role": "primary",
      "contamination_risk": 0.0,
      "domain_cues": []
    },
    {
      "doc_id": "D2",
      "relevance": "low",
      "answer_candidate": "unknown",
      "normalized_answer": "unknown",
      "claim": "",
      "temporal_status": "unknown",
      "time_cue": "unknown",
      "confidence": 0.0,
      "raw_quote": "",
      "rationale": "card_error: Unterminated string starting at: line 10 column 16 (char 417); heuristic fallback used",
      "entity_explicitness": "unknown",
      "answer_role": "primary",
      "contamination_risk": 0.0,
      "domain_cues": []
    },
    {
      "doc_id": "D3",
      "relevance": "high",
      "answer_candidate": "UK",
      "normalized_answer": "uk",
      "claim": "No. 100 Squadron RAF was re-formed in the UK on 15 December 1942.",
      "temporal_status": "current",
      "time_cue": "15 December 1942",
      "confidence": 0.95,
      "raw_quote": "On 15 December 1942, No. 100 Squadron RAF proper was re-formed in the UK",
      "rationale": "The document explicitly states the re-formation location of 100 Squadron RAF.",
      "entity_explicitness": "unknown",
      "answer_role": "primary",
      "contamination_risk": 0.0,
      "domain_cues": []
    }
  ],
  "duplicate_groups": [
    {
      "group_id": "G1",
      "doc_ids": [
        "D1"
      ],
      "representative_doc_id": "D1",
      "answer_candidate": "Australia"
    },
    {
      "group_id": "G2",
      "doc_ids": [
        "D2"
      ],
      "representative_doc_id": "D2",
      "answer_candidate": "unknown"
    },
    {
      "group_id": "G3",
      "doc_ids": [
        "D3"
      ],
      "representative_doc_id": "D3",
      "answer_candidate": "UK"
    }
  ],
  "conflict_edges": [
    {
      "src": "D1",
      "dst": "D3",
      "relation": "contradict",
      "reason": "D1 supports 'Australia', while D3 supports 'UK'.",
      "confidence": 0.85
    }
  ],
  "answer_clusters": [
    {
      "answer": "Australia",
      "normalized_answer": "australia",
      "doc_ids": [
        "D1"
      ],
      "duplicate_group_ids": [
        "G1"
      ],
      "unique_support_count": 1,
      "high_relevance_count": 1,
      "explicit_support_count": 0,
      "missing_entity_count": 0,
      "primary_support_count": 1,
      "mean_contamination_risk": 0.0,
      "mean_confidence": 1.0,
      "conflict_count": 1,
      "score": 1.98
    },
    {
      "answer": "UK",
      "normalized_answer": "uk",
      "doc_ids": [
        "D3"
      ],
      "duplicate_group_ids": [
        "G3"
      ],
      "unique_support_count": 1,
      "high_relevance_count": 1,
      "explicit_support_count": 0,
      "missing_entity_count": 0,
      "primary_support_count": 1,
      "mean_contamination_risk": 0.0,
      "mean_confidence": 0.95,
      "conflict_count": 1,
      "score": 1.9675
    }
  ],
  "candidate_decision": {
    "mode": "conflict",
    "answer": "conflict",
    "supporting_doc_ids": [
      "D1",
      "D3"
    ],
    "rejected_doc_ids": [],
    "reason": "Multiple answer clusters have similar support.",
    "scores": {
      "Australia": 1.98,
      "UK": 1.9675
    }
  },
  "verifier_decision": {
    "verdict": "conflict",
    "final_answer": "conflict",
    "supporting_doc_ids": [
      "D1",
      "D3"
    ],
    "rejected_doc_ids": [],
    "reason": "Multiple answer clusters have similar support."
  },
  "final_answer": "conflict",
  "decision_trace": [
    "Extracted 3 evidence cards.",
    "Built 3 duplicate groups.",
    "Built 1 evidence graph edges.",
    "Built 2 answer clusters.",
    "Candidate decision: conflict -> conflict.",
    "Verifier decision: conflict -> conflict."
  ]
}